telegramy/__init__.py
telegramy/main.py
telegramy/telegram_manager.py
telegramy-0.0.2.dist-info/LICENSE
telegramy-0.0.2.dist-info/METADATA
telegramy-0.0.2.dist-info/WHEEL
telegramy-0.0.2.dist-info/top_level.txt
telegramy-0.0.2.dist-info/RECORD
