Metadata-Version: 2.1
Name: telegramy
Version: 0.0.2
Summary: A Python package to send messages and images to Telegram groups using 'requests' package only.
Author: Yan Sido
Author-email: yansido1@gmail.com
Keywords: python,telegram,telegram-sender,telegram sender,telegramy,telegramy sender,telegramy python,telegramy sender python
Classifier: Development Status :: 3 - Alpha
Classifier: Intended Audience :: Developers
Classifier: Programming Language :: Python :: 3
Classifier: Operating System :: Unix
Classifier: Operating System :: MacOS :: MacOS X
Classifier: Operating System :: Microsoft :: Windows
License-File: LICENSE
Requires-Dist: requests
